Assignment-2-P2/traffic_light.v
module traffic_light(
    input wire clk,
    input wire rst,   // synchronous active-high reset
    input wire tick,  // 1 Hz tick pulse
    output reg ns_g, ns_y, ns_r,
    output reg ew_g, ew_y, ew_r
);

    // State encoding (binary)
    parameter NS_GREEN  = 2'b00;
    parameter NS_YELLOW = 2'b01;
    parameter EW_GREEN  = 2'b10;
    parameter EW_YELLOW = 2'b11;

    reg [1:0] state_q, state_d;
    reg [3:0] tick_count_q, tick_count_d;

    // State duration constants
    parameter NS_G_TIME = 5;
    parameter NS_Y_TIME = 2;
    parameter EW_G_TIME = 5;
    parameter EW_Y_TIME = 2;

    // Sequential: state & counter update
    always @(posedge clk) begin
        if (rst) begin
            state_q <= NS_GREEN;
            tick_count_q <= 0;
        end else begin
            state_q <= state_d;
            tick_count_q <= tick_count_d;
        end
    end

    // Next-state logic
    always @(*) begin
        state_d = state_q;
        tick_count_d = tick_count_q;

        if (tick) begin
            tick_count_d = tick_count_q + 1;
            case (state_q)
                NS_GREEN:  if (tick_count_q == NS_G_TIME-1) begin
                               state_d = NS_YELLOW;
                               tick_count_d = 0;
                           end
                NS_YELLOW: if (tick_count_q == NS_Y_TIME-1) begin
                               state_d = EW_GREEN;
                               tick_count_d = 0;
                           end
                EW_GREEN:  if (tick_count_q == EW_G_TIME-1) begin
                               state_d = EW_YELLOW;
                               tick_count_d = 0;
                           end
                EW_YELLOW: if (tick_count_q == EW_Y_TIME-1) begin
                               state_d = NS_GREEN;
                               tick_count_d = 0;
                           end
            endcase
        end
    end

    // Moore outputs
    always @(*) begin
        ns_g=0; ns_y=0; ns_r=0;
        ew_g=0; ew_y=0; ew_r=0;

        case (state_q)
            NS_GREEN:  begin ns_g=1; ew_r=1; end
            NS_YELLOW: begin ns_y=1; ew_r=1; end
            EW_GREEN:  begin ew_g=1; ns_r=1; end
            EW_YELLOW: begin ew_y=1; ns_r=1; end
        endcase
    end

endmodule

Assignment-2-P2/tb_traffic_light.v
`timescale 1ns/1ps

module tb_traffic_light;

    reg clk, rst, tick;
    wire ns_g, ns_y, ns_r, ew_g, ew_y, ew_r;

    // DUT
    traffic_light dut (
        .clk(clk), .rst(rst), .tick(tick),
        .ns_g(ns_g), .ns_y(ns_y), .ns_r(ns_r),
        .ew_g(ew_g), .ew_y(ew_y), .ew_r(ew_r)
    );

    // Clock generator
    always #5 clk = ~clk; // 100 MHz simulation clock

    initial begin
        $dumpfile("traffic_light.vcd");
        $dumpvars(0, tb_traffic_light);

        clk = 0; rst = 1; tick = 0;
        #20 rst = 0;

        // Generate 1 Hz tick (simulate with 50 cycles)
        repeat (40) begin
            #50 tick = 1;
            #10 tick = 0;
        end

        #100 $finish;
    end

endmodule

Assignment-2-P2/traffic_light.vcd
$date
	Mon Aug 18 20:27:33 2025
$end
$version
	Icarus Verilog
$end
$timescale
	1ps
$end
$scope module tb_traffic_light $end
$var wire 1 ! ns_y $end
$var wire 1 " ns_r $end
$var wire 1 # ns_g $end
$var wire 1 $ ew_y $end
$var wire 1 % ew_r $end
$var wire 1 & ew_g $end
$var reg 1 ' clk $end
$var reg 1 ( rst $end
$var reg 1 ) tick $end
$scope module dut $end
$var wire 1 ' clk $end
$var wire 1 ( rst $end
$var wire 1 ) tick $end
$var parameter 2 * EW_GREEN $end
$var parameter 32 + EW_G_TIME $end
$var parameter 2 , EW_YELLOW $end
$var parameter 32 - EW_Y_TIME $end
$var parameter 2 . NS_GREEN $end
$var parameter 32 / NS_G_TIME $end
$var parameter 2 0 NS_YELLOW $end
$var parameter 32 1 NS_Y_TIME $end
$var reg 1 & ew_g $end
$var reg 1 % ew_r $end
$var reg 1 $ ew_y $end
$var reg 1 # ns_g $end
$var reg 1 " ns_r $end
$var reg 1 ! ns_y $end
$var reg 2 2 state_d [1:0] $end
$var reg 2 3 state_q [1:0] $end
$var reg 4 4 tick_count_d [3:0] $end
$var reg 4 5 tick_count_q [3:0] $end
$upscope $end
$upscope $end
$enddefinitions $end
$comment Show the parameter values. $end
$dumpall
b10 1
b1 0
b101 /
b0 .
b10 -
b11 ,
b101 +
b10 *
$end
#0
$dumpvars
bx 5
bx 4
bx 3
bx 2
0)
1(
0'
x&
x%
x$
x#
x"
x!
$end
#5000
1%
0$
0&
0"
0!
1#
b0 4
b0 2
b0 5
b0 3
1'
#10000
0'
#15000
1'
#20000
0'
0(
#25000
1'
#30000
0'
#35000
1'
#40000
0'
#45000
1'
#50000
0'
#55000
1'
#60000
0'
#65000
1'
#70000
b1 4
0'
1)
#75000
b10 4
b1 5
1'
#80000
b1 4
0'
0)
#85000
1'
#90000
0'
#95000
1'
#100000
0'
#105000
1'
#110000
0'
#115000
1'
#120000
0'
#125000
1'
#130000
b10 4
0'
1)
#135000
b11 4
b10 5
1'
#140000
b10 4
0'
0)
#145000
1'
#150000
0'
#155000
1'
#160000
0'
#165000
1'
#170000
0'
#175000
1'
#180000
0'
#185000
1'
#190000
b11 4
0'
1)
#195000
b100 4
b11 5
1'
#200000
b11 4
0'
0)
#205000
1'
#210000
0'
#215000
1'
#220000
0'
#225000
1'
#230000
0'
#235000
1'
#240000
0'
#245000
1'
#250000
b100 4
0'
1)
#255000
b1 2
b0 4
b100 5
1'
#260000
b100 4
b0 2
0'
0)
#265000
1'
#270000
0'
#275000
1'
#280000
0'
#285000
1'
#290000
0'
#295000
1'
#300000
0'
#305000
1'
#310000
b1 2
b0 4
0'
1)
#315000
1!
1%
0#
b1 4
b0 5
b1 3
1'
#320000
b0 4
0'
0)
#325000
1'
#330000
0'
#335000
1'
#340000
0'
#345000
1'
#350000
0'
#355000
1'
#360000
0'
#365000
1'
#370000
b1 4
0'
1)
#375000
b10 2
b0 4
b1 5
1'
#380000
b1 4
b1 2
0'
0)
#385000
1'
#390000
0'
#395000
1'
#400000
0'
#405000
1'
#410000
0'
#415000
1'
#420000
0'
#425000
1'
#430000
b10 2
b0 4
0'
1)
#435000
1"
1&
0%
0!
b1 4
b0 5
b10 3
1'
#440000
b0 4
0'
0)
#445000
1'
#450000
0'
#455000
1'
#460000
0'
#465000
1'
#470000
0'
#475000
1'
#480000
0'
#485000
1'
#490000
b1 4
0'
1)
#495000
b10 4
b1 5
1'
#500000
b1 4
0'
0)
#505000
1'
#510000
0'
#515000
1'
#520000
0'
#525000
1'
#530000
0'
#535000
1'
#540000
0'
#545000
1'
#550000
b10 4
0'
1)
#555000
b11 4
b10 5
1'
#560000
b10 4
0'
0)
#565000
1'
#570000
0'
#575000
1'
#580000
0'
#585000
1'
#590000
0'
#595000
1'
#600000
0'
#605000
1'
#610000
b11 4
0'
1)
#615000
b100 4
b11 5
1'
#620000
b11 4
0'
0)
#625000
1'
#630000
0'
#635000
1'
#640000
0'
#645000
1'
#650000
0'
#655000
1'
#660000
0'
#665000
1'
#670000
b100 4
0'
1)
#675000
b11 2
b0 4
b100 5
1'
#680000
b100 4
b10 2
0'
0)
#685000
1'
#690000
0'
#695000
1'
#700000
0'
#705000
1'
#710000
0'
#715000
1'
#720000
0'
#725000
1'
#730000
b11 2
b0 4
0'
1)
#735000
1$
0&
1"
b1 4
b0 5
b11 3
1'
#740000
b0 4
0'
0)
#745000
1'
#750000
0'
#755000
1'
#760000
0'
#765000
1'
#770000
0'
#775000
1'
#780000
0'
#785000
1'
#790000
b1 4
0'
1)
#795000
b0 2
b0 4
b1 5
1'
#800000
b1 4
b11 2
0'
0)
#805000
1'
#810000
0'
#815000
1'
#820000
0'
#825000
1'
#830000
0'
#835000
1'
#840000
0'
#845000
1'
#850000
b0 2
b0 4
0'
1)
#855000
1%
1#
0$
0"
b1 4
b0 5
b0 3
1'
#860000
b0 4
0'
0)
#865000
1'
#870000
0'
#875000
1'
#880000
0'
#885000
1'
#890000
0'
#895000
1'
#900000
0'
#905000
1'
#910000
b1 4
0'
1)
#915000
b10 4
b1 5
1'
#920000
b1 4
0'
0)
#925000
1'
#930000
0'
#935000
1'
#940000
0'
#945000
1'
#950000
0'
#955000
1'
#960000
0'
#965000
1'
#970000
b10 4
0'
1)
#975000
b11 4
b10 5
1'
#980000
b10 4
0'
0)
#985000
1'
#990000
0'
#995000
1'
#1000000
0'
#1005000
1'
#1010000
0'
#1015000
1'
#1020000
0'
#1025000
1'
#1030000
b11 4
0'
1)
#1035000
b100 4
b11 5
1'
#1040000
b11 4
0'
0)
#1045000
1'
#1050000
0'
#1055000
1'
#1060000
0'
#1065000
1'
#1070000
0'
#1075000
1'
#1080000
0'
#1085000
1'
#1090000
b100 4
0'
1)
#1095000
b1 2
b0 4
b100 5
1'
#1100000
b100 4
b0 2
0'
0)
#1105000
1'
#1110000
0'
#1115000
1'
#1120000
0'
#1125000
1'
#1130000
0'
#1135000
1'
#1140000
0'
#1145000
1'
#1150000
b1 2
b0 4
0'
1)
#1155000
1!
1%
0#
b1 4
b0 5
b1 3
1'
#1160000
b0 4
0'
0)
#1165000
1'
#1170000
0'
#1175000
1'
#1180000
0'
#1185000
1'
#1190000
0'
#1195000
1'
#1200000
0'
#1205000
1'
#1210000
b1 4
0'
1)
#1215000
b10 2
b0 4
b1 5
1'
#1220000
b1 4
b1 2
0'
0)
#1225000
1'
#1230000
0'
#1235000
1'
#1240000
0'
#1245000
1'
#1250000
0'
#1255000
1'
#1260000
0'
#1265000
1'
#1270000
b10 2
b0 4
0'
1)
#1275000
1"
1&
0%
0!
b1 4
b0 5
b10 3
1'
#1280000
b0 4
0'
0)
#1285000
1'
#1290000
0'
#1295000
1'
#1300000
0'
#1305000
1'
#1310000
0'
#1315000
1'
#1320000
0'
#1325000
1'
#1330000
b1 4
0'
1)
#1335000
b10 4
b1 5
1'
#1340000
b1 4
0'
0)
#1345000
1'
#1350000
0'
#1355000
1'
#1360000
0'
#1365000
1'
#1370000
0'
#1375000
1'
#1380000
0'
#1385000
1'
#1390000
b10 4
0'
1)
#1395000
b11 4
b10 5
1'
#1400000
b10 4
0'
0)
#1405000
1'
#1410000
0'
#1415000
1'
#1420000
0'
#1425000
1'
#1430000
0'
#1435000
1'
#1440000
0'
#1445000
1'
#1450000
b11 4
0'
1)
#1455000
b100 4
b11 5
1'
#1460000
b11 4
0'
0)
#1465000
1'
#1470000
0'
#1475000
1'
#1480000
0'
#1485000
1'
#1490000
0'
#1495000
1'
#1500000
0'
#1505000
1'
#1510000
b100 4
0'
1)
#1515000
b11 2
b0 4
b100 5
1'
#1520000
b100 4
b10 2
0'
0)
#1525000
1'
#1530000
0'
#1535000
1'
#1540000
0'
#1545000
1'
#1550000
0'
#1555000
1'
#1560000
0'
#1565000
1'
#1570000
b11 2
b0 4
0'
1)
#1575000
1$
0&
1"
b1 4
b0 5
b11 3
1'
#1580000
b0 4
0'
0)
#1585000
1'
#1590000
0'
#1595000
1'
#1600000
0'
#1605000
1'
#1610000
0'
#1615000
1'
#1620000
0'
#1625000
1'
#1630000
b1 4
0'
1)
#1635000
b0 2
b0 4
b1 5
1'
#1640000
b1 4
b11 2
0'
0)
#1645000
1'
#1650000
0'
#1655000
1'
#1660000
0'
#1665000
1'
#1670000
0'
#1675000
1'
#1680000
0'
#1685000
1'
#1690000
b0 2
b0 4
0'
1)
#1695000
1%
1#
0$
0"
b1 4
b0 5
b0 3
1'
#1700000
b0 4
0'
0)
#1705000
1'
#1710000
0'
#1715000
1'
#1720000
0'
#1725000
1'
#1730000
0'
#1735000
1'
#1740000
0'
#1745000
1'
#1750000
b1 4
0'
1)
#1755000
b10 4
b1 5
1'
#1760000
b1 4
0'
0)
#1765000
1'
#1770000
0'
#1775000
1'
#1780000
0'
#1785000
1'
#1790000
0'
#1795000
1'
#1800000
0'
#1805000
1'
#1810000
b10 4
0'
1)
#1815000
b11 4
b10 5
1'
#1820000
b10 4
0'
0)
#1825000
1'
#1830000
0'
#1835000
1'
#1840000
0'
#1845000
1'
#1850000
0'
#1855000
1'
#1860000
0'
#1865000
1'
#1870000
b11 4
0'
1)
#1875000
b100 4
b11 5
1'
#1880000
b11 4
0'
0)
#1885000
1'
#1890000
0'
#1895000
1'
#1900000
0'
#1905000
1'
#1910000
0'
#1915000
1'
#1920000
0'
#1925000
1'
#1930000
b100 4
0'
1)
#1935000
b1 2
b0 4
b100 5
1'
#1940000
b100 4
b0 2
0'
0)
#1945000
1'
#1950000
0'
#1955000
1'
#1960000
0'
#1965000
1'
#1970000
0'
#1975000
1'
#1980000
0'
#1985000
1'
#1990000
b1 2
b0 4
0'
1)
#1995000
1!
1%
0#
b1 4
b0 5
b1 3
1'
#2000000
b0 4
0'
0)
#2005000
1'
#2010000
0'
#2015000
1'
#2020000
0'
#2025000
1'
#2030000
0'
#2035000
1'
#2040000
0'
#2045000
1'
#2050000
b1 4
0'
1)
#2055000
b10 2
b0 4
b1 5
1'
#2060000
b1 4
b1 2
0'
0)
#2065000
1'
#2070000
0'
#2075000
1'
#2080000
0'
#2085000
1'
#2090000
0'
#2095000
1'
#2100000
0'
#2105000
1'
#2110000
b10 2
b0 4
0'
1)
#2115000
1"
1&
0%
0!
b1 4
b0 5
b10 3
1'
#2120000
b0 4
0'
0)
#2125000
1'
#2130000
0'
#2135000
1'
#2140000
0'
#2145000
1'
#2150000
0'
#2155000
1'
#2160000
0'
#2165000
1'
#2170000
b1 4
0'
1)
#2175000
b10 4
b1 5
1'
#2180000
b1 4
0'
0)
#2185000
1'
#2190000
0'
#2195000
1'
#2200000
0'
#2205000
1'
#2210000
0'
#2215000
1'
#2220000
0'
#2225000
1'
#2230000
b10 4
0'
1)
#2235000
b11 4
b10 5
1'
#2240000
b10 4
0'
0)
#2245000
1'
#2250000
0'
#2255000
1'
#2260000
0'
#2265000
1'
#2270000
0'
#2275000
1'
#2280000
0'
#2285000
1'
#2290000
b11 4
0'
1)
#2295000
b100 4
b11 5
1'
#2300000
b11 4
0'
0)
#2305000
1'
#2310000
0'
#2315000
1'
#2320000
0'
#2325000
1'
#2330000
0'
#2335000
1'
#2340000
0'
#2345000
1'
#2350000
b100 4
0'
1)
#2355000
b11 2
b0 4
b100 5
1'
#2360000
b100 4
b10 2
0'
0)
#2365000
1'
#2370000
0'
#2375000
1'
#2380000
0'
#2385000
1'
#2390000
0'
#2395000
1'
#2400000
0'
#2405000
1'
#2410000
b11 2
b0 4
0'
1)
#2415000
1$
0&
1"
b1 4
b0 5
b11 3
1'
#2420000
b0 4
0'
0)
