Assignment-2-P3/vending_mealy.v
module vending_mealy(
    input wire clk,
    input wire rst,         // synchronous active-high reset
    input wire [1:0] coin,  // 01=5, 10=10, 00=idle
    output reg dispense,    // 1-cycle pulse
    output reg chg5         // 1-cycle pulse
);

    // State encoding
    parameter S0  = 2'b00;
    parameter S5  = 2'b01;
    parameter S10 = 2'b10;
    parameter S15 = 2'b11;

    reg [1:0] state_q, state_d;

    // Sequential state register
    always @(posedge clk) begin
        if (rst)
            state_q <= S0;
        else
            state_q <= state_d;
    end

    // Next-state + Mealy outputs
    always @(*) begin
        state_d   = state_q;
        dispense  = 0;
        chg5      = 0;

        case (state_q)
            S0: begin
                if (coin == 2'b01) state_d = S5;          // insert 5
                else if (coin == 2'b10) state_d = S10;    // insert 10
            end

            S5: begin
                if (coin == 2'b01) state_d = S10;         // +5
                else if (coin == 2'b10) state_d = S15;    // +10
            end

            S10: begin
                if (coin == 2'b01) state_d = S15;         // +5
                else if (coin == 2'b10) begin             // +10 => 20
                    dispense = 1;
                    state_d  = S0;
                end
            end

            S15: begin
                if (coin == 2'b01) begin                  // +5 => 20
                    dispense = 1;
                    state_d  = S0;
                end
                else if (coin == 2'b10) begin             // +10 => 25
                    dispense = 1;
                    chg5     = 1;
                    state_d  = S0;
                end
            end
        endcase
    end

endmodule

Assignment-2-P3/tb_vending_mealy.v
`timescale 1ns/1ps

module tb_vending_mealy;

    reg clk, rst;
    reg [1:0] coin;
    wire dispense, chg5;

    // DUT
    vending_mealy dut (
        .clk(clk),
        .rst(rst),
        .coin(coin),
        .dispense(dispense),
        .chg5(chg5)
    );

    // Clock generation
    always #5 clk = ~clk; // 100 MHz simulation

    initial begin
        $dumpfile("vending_mealy.vcd");
        $dumpvars(0, tb_vending_mealy);

        clk = 0; rst = 1; coin = 2'b00;
        #15 rst = 0;

        // Insert 5 + 5 + 10 = 20 → should vend
        #10 coin = 2'b01; #10 coin = 2'b00; 
        #10 coin = 2'b01; #10 coin = 2'b00;
        #10 coin = 2'b10; #10 coin = 2'b00;

        // Insert 10 + 10 = 20 → should vend
        #10 coin = 2'b10; #10 coin = 2'b00;
        #10 coin = 2'b10; #10 coin = 2'b00;

        // Insert 15 + 10 = 25 → vend + change
        #10 coin = 2'b10; #10 coin = 2'b00;
        #10 coin = 2'b01; #10 coin = 2'b00;
        #10 coin = 2'b10; #10 coin = 2'b00;

        #50 $finish;
    end

endmodule

Assignment-2-P3/vending_mealy.vcd
$date
	Mon Aug 18 20:34:56 2025
$end
$version
	Icarus Verilog
$end
$timescale
	1ps
$end
$scope module tb_vending_mealy $end
$var wire 1 ! dispense $end
$var wire 1 " chg5 $end
$var reg 1 # clk $end
$var reg 2 $ coin [1:0] $end
$var reg 1 % rst $end
$scope module dut $end
$var wire 1 # clk $end
$var wire 2 & coin [1:0] $end
$var wire 1 % rst $end
$var parameter 2 ' S0 $end
$var parameter 2 ( S10 $end
$var parameter 2 ) S15 $end
$var parameter 2 * S5 $end
$var reg 1 " chg5 $end
$var reg 1 ! dispense $end
$var reg 2 + state_d [1:0] $end
$var reg 2 , state_q [1:0] $end
$upscope $end
$upscope $end
$enddefinitions $end
$comment Show the parameter values. $end
$dumpall
b1 *
b11 )
b10 (
b0 '
$end
#0
$dumpvars
bx ,
bx +
b0 &
1%
b0 $
0#
0"
0!
$end
#5000
b0 +
b0 ,
1#
#10000
0#
#15000
1#
0%
#20000
0#
#25000
b1 ,
b10 +
1#
b1 $
b1 &
#30000
0#
#35000
b1 +
1#
b0 $
b0 &
#40000
0#
#45000
b10 ,
b11 +
1#
b1 $
b1 &
#50000
0#
#55000
b10 +
1#
b0 $
b0 &
#60000
0#
#65000
b0 ,
b10 +
0!
1#
b10 $
b10 &
#70000
0#
#75000
b0 +
1#
b0 $
b0 &
#80000
0#
#85000
1!
b10 ,
b0 +
1#
b10 $
b10 &
#90000
0#
#95000
0!
b10 +
1#
b0 $
b0 &
#100000
0#
#105000
b0 ,
b10 +
0!
1#
b10 $
b10 &
#110000
0#
#115000
b0 +
1#
b0 $
b0 &
#120000
0#
#125000
1!
b10 ,
b0 +
1#
b10 $
b10 &
#130000
0#
#135000
0!
b10 +
1#
b0 $
b0 &
#140000
0#
#145000
1!
b11 ,
b0 +
1#
b1 $
b1 &
#150000
0#
#155000
0!
b11 +
1#
b0 $
b0 &
#160000
0#
#165000
b0 ,
b10 +
0"
0!
1#
b10 $
b10 &
#170000
0#
#175000
b0 +
1#
b0 $
b0 &
