p1/seq_detect_mealy.v
module seq_detect_mealy (
    input  wire clk,
    input  wire rst,    // sync active-high
    input  wire din,    // serial input bit per clock
    output reg  y       // 1-cycle pulse when pattern ...1101 seen
);

    localparam [1:0] IDLE          = 2'd0, // waiting for '1'
                     GOT1          = 2'd1, // seen '1'
                     GOT11         = 2'd2, // seen "11"
                     GOT110        = 2'd3; // seen "110"

    reg [1:0] state_q, state_d; // present and next state

    // Next-state logic and Mealy output
    always @(*) begin
        state_d = state_q;
        y = 1'b0;

        case (state_q)
            IDLE: begin
                if (din) state_d = GOT1;
                else     state_d = IDLE;
            end

            GOT1: begin
                if (din) state_d = GOT11;
                else     state_d = IDLE;
            end

            GOT11: begin
                if (din) state_d = GOT11;   // "111" still contains suffix "11"
                else     state_d = GOT110;
            end

            GOT110: begin
                if (din) begin
                    y       = 1'b1;    // detected 1101
                    state_d = GOT1;    // last '1' may start a new match
                end
                else begin
                    state_d = IDLE;
                end
            end
        endcase
    end

    // State register (synchronous active-high reset)
    always @(posedge clk) begin
        if (rst) begin
            state_q <= IDLE;
        end
        else begin
            state_q <= state_d;
        end
    end

endmodule

p1/seq_detect_mealy_tb.v
`timescale 1ns/1ps

module tb_seq_detect_mealy;

    reg clk, rst, din;
    wire y;

    // Instantiate DUT
    seq_detect_mealy dut (
        .clk(clk),
        .rst(rst),
        .din(din),
        .y(y)
    );

    always #5 clk = ~clk;

    initial begin
        $dumpfile("p1.vcd");
        $dumpvars(0, tb_seq_detect_mealy);

        // Init
        clk = 0;
        rst = 1;
        din = 0;

        // Reset for a little while
        #12 rst = 0;

        // Example input sequence: 1101101 (contains overlapping 1101 twice)
        din = 1; #10;
        din = 1; #10;
        din = 0; #10;
        din = 1; #10;  // first detection here
        din = 1; #10;
        din = 0; #10;
        din = 1; #10;  // second detection here

        #20 $finish;
    end

    // Monitor values(outputs)
    initial begin
        $monitor("Time=%0t | din=%b | y=%b | state_q=%0d",
                  $time, din, y, dut.state_q);
    end

endmodule

p1/p1.vcd
$date
	Mon Aug 18 20:06:45 2025
$end
$version
	Icarus Verilog
$end
$timescale
	1ps
$end
$scope module tb_seq_detect_mealy $end
$var wire 1 ! y $end
$var reg 1 " clk $end
$var reg 1 # din $end
$var reg 1 $ rst $end
$scope module dut $end
$var wire 1 " clk $end
$var wire 1 # din $end
$var wire 1 $ rst $end
$var parameter 2 % GOT1 $end
$var parameter 2 & GOT11 $end
$var parameter 2 ' GOT110 $end
$var parameter 2 ( IDLE $end
$var reg 2 ) state_d [1:0] $end
$var reg 2 * state_q [1:0] $end
$var reg 1 ! y $end
$upscope $end
$upscope $end
$enddefinitions $end
$comment Show the parameter values. $end
$dumpall
b0 (
b11 '
b10 &
b1 %
$end
#0
$dumpvars
bx *
bx )
1$
0#
0"
0!
$end
#5000
b0 )
b0 *
1"
#10000
0"
#12000
b1 )
1#
0$
#15000
b10 )
b1 *
1"
#20000
0"
#25000
b10 *
1"
#30000
0"
#32000
b11 )
0#
#35000
b0 )
b11 *
1"
#40000
0"
#42000
1!
b1 )
1#
#45000
b10 )
0!
b1 *
1"
#50000
0"
#55000
b10 *
1"
#60000
0"
#62000
b11 )
0#
#65000
b0 )
b11 *
1"
#70000
0"
#72000
1!
b1 )
1#
#75000
b10 )
0!
b1 *
1"
#80000
0"
#85000
b10 *
1"
